minichat/__init__.py
minichat/aiml_data/alice/ai.aiml
minichat/aiml_data/alice/alice.aiml
minichat/aiml_data/alice/astrology.aiml
minichat/aiml_data/alice/atomic.aiml
minichat/aiml_data/alice/badanswer.aiml
minichat/aiml_data/alice/biography.aiml
minichat/aiml_data/alice/bot.aiml
minichat/aiml_data/alice/bot_profile.aiml
minichat/aiml_data/alice/client.aiml
minichat/aiml_data/alice/client_profile.aiml
minichat/aiml_data/alice/computers.aiml
minichat/aiml_data/alice/continuation.aiml
minichat/aiml_data/alice/copyme.aiml
minichat/aiml_data/alice/currency.aiml
minichat/aiml_data/alice/custom.aiml
minichat/aiml_data/alice/date.aiml
minichat/aiml_data/alice/def.aiml
minichat/aiml_data/alice/default.aiml
minichat/aiml_data/alice/drphil.aiml
minichat/aiml_data/alice/drugs.aiml
minichat/aiml_data/alice/emotion.aiml
minichat/aiml_data/alice/food.aiml
minichat/aiml_data/alice/geography.aiml
minichat/aiml_data/alice/gossip.aiml
minichat/aiml_data/alice/happy.aiml
minichat/aiml_data/alice/history.aiml
minichat/aiml_data/alice/humor.aiml
minichat/aiml_data/alice/imponderables.aiml
minichat/aiml_data/alice/inquiry.aiml
minichat/aiml_data/alice/interjection.aiml
minichat/aiml_data/alice/iu.aiml
minichat/aiml_data/alice/jokes.aiml
minichat/aiml_data/alice/knowledge.aiml
minichat/aiml_data/alice/literature.aiml
minichat/aiml_data/alice/loebner10.aiml
minichat/aiml_data/alice/money.aiml
minichat/aiml_data/alice/movies.aiml
minichat/aiml_data/alice/mp0.aiml
minichat/aiml_data/alice/mp1.aiml
minichat/aiml_data/alice/mp2.aiml
minichat/aiml_data/alice/mp3.aiml
minichat/aiml_data/alice/mp4.aiml
minichat/aiml_data/alice/mp5.aiml
minichat/aiml_data/alice/mp6.aiml
minichat/aiml_data/alice/music.aiml
minichat/aiml_data/alice/numbers.aiml
minichat/aiml_data/alice/personality.aiml
minichat/aiml_data/alice/phone.aiml
minichat/aiml_data/alice/pickup.aiml
minichat/aiml_data/alice/politics.aiml
minichat/aiml_data/alice/primeminister.aiml
minichat/aiml_data/alice/primitive-math.aiml
minichat-1.0.3.dist-info/LICENSE
minichat-1.0.3.dist-info/WHEEL
minichat-1.0.3.dist-info/METADATA
minichat-1.0.3.dist-info/RECORD
